{"v":"5.8.1","fr":30,"ip":0,"op":48,"w":500,"h":500,"nm":"à¹à¸à¹à¸","ddd":0,"assets":[],"layers":[{"ddd":0,"ind":1,"ty":4,"nm":"Layer 8 Outlines","sr":1,"ks":{"o":{"a":0,"k":100,"ix":11},"r":{"a":1,"k":[{"i":{"x":[0.667],"y":[0.986]},"o":{"x":[0.756],"y":[0]},"t":18,"s":[0]},{"t":28,"s":[-7.682]}],"ix":10},"p":{"a":1,"k":[{"i":{"x":0.667,"y":1},"o":{"x":0.756,"y":0},"t":18,"s":[250,250,0],"to":[0,0,0],"ti":[0,0,0]},{"t":28,"s":[244.874,241.12,0]}],"ix":2,"l":2},"a":{"a":0,"k":[250,250,0],"ix":1,"l":2},"s":{"a":1,"k":[{"i":{"x":[0.667,0.667,0.667],"y":[1.037,1.037,1]},"o":{"x":[0.756,0.756,0.333],"y":[0,0,0]},"t":18,"s":[100,100,100]},{"t":28,"s":[103,103,100]}],"ix":6,"l":2}},"ao":0,"shapes":[{"ty":"gr","it":[{"ind":0,"ty":"sh","ix":1,"ks":{"a":0,"k":{"i":[[0,-10.366],[37.544,-3.462],[42.64,0],[27.257,2.547],[0,13.845],[-23.2,7.431],[-7.562,11.245],[-41.142,0],[-19.114,-28.41],[-12.902,-4.141]],"o":[[0,13.845],[-27.257,2.547],[-42.64,0],[-37.593,-3.462],[0,-10.403],[12.905,-4.134],[19.103,-28.41],[41.102,0],[7.564,11.242],[23.187,7.442]],"v":[[164.527,35.646],[105.783,59.971],[0.024,63.143],[-105.734,59.971],[-164.527,35.646],[-127.402,8.283],[-96.087,-15.604],[0.024,-63.143],[96.133,-15.604],[127.445,8.288]],"c":true},"ix":2},"nm":"Path 1","mn":"ADBE Vector Shape - Group","hd":false},{"ty":"fl","c":{"a":0,"k":[0.960784373564,0.549019607843,0.003921568627,1],"ix":4},"o":{"a":0,"k":100,"ix":5},"r":1,"bm":0,"nm":"Fill 1","mn":"ADBE Vector Graphic - Fill","hd":false},{"ty":"tr","p":{"a":0,"k":[250,287.232],"ix":2},"a":{"a":0,"k":[0,0],"ix":1},"s":{"a":0,"k":[100,100],"ix":3},"r":{"a":0,"k":0,"ix":6},"o":{"a":0,"k":100,"ix":7},"sk":{"a":0,"k":0,"ix":4},"sa":{"a":0,"k":0,"ix":5},"nm":"Transform"}],"nm":"Group 1","np":2,"cix":2,"bm":0,"ix":1,"mn":"ADBE Vector Group","hd":false}],"ip":0,"op":90,"st":0,"bm":0},{"ddd":0,"ind":2,"ty":4,"nm":"Layer 7 Outlines","parent":1,"sr":1,"ks":{"o":{"a":0,"k":100,"ix":11},"r":{"a":1,"k":[{"i":{"x":[0.667],"y":[1.003]},"o":{"x":[0.756],"y":[0]},"t":18,"s":[0]},{"t":28,"s":[32.057]}],"ix":10},"p":{"a":1,"k":[{"i":{"x":0.667,"y":1},"o":{"x":0.756,"y":0},"t":18,"s":[250,250,0],"to":[0,0,0],"ti":[0,0,0]},{"t":28,"s":[341.479,318.807,0]}],"ix":2,"l":2},"a":{"a":0,"k":[250,250,0],"ix":1,"l":2},"s":{"a":0,"k":[100,100,100],"ix":6,"l":2}},"ao":0,"shapes":[{"ty":"gr","it":[{"ind":0,"ty":"sh","ix":1,"ks":{"a":0,"k":{"i":[[-11.874,-32.756],[19.305,4.367],[2.329,0.108],[1.223,-0.033],[0.839,-0.102],[1.183,-0.216],[8.469,-5.817],[-4.842,2.319]],"o":[[-7.077,-17.485],[-2.309,-0.491],[-1.219,0.025],[-0.838,0.103],[-1.179,0.064],[-9.957,2.496],[4.372,-3.17],[33.84,-17.455]],"v":[[43.556,26.117],[4.225,-13.38],[-3.337,-14.307],[-7.581,-14.206],[-10.956,-13.802],[-15.961,-12.822],[-43.555,0.441],[-29.006,-8.662]],"c":true},"ix":2},"nm":"Path 1","mn":"ADBE Vector Shape - Group","hd":false},{"ty":"fl","c":{"a":0,"k":[0.866666726505,0.156862745098,0.062745098039,1],"ix":4},"o":{"a":0,"k":100,"ix":5},"r":1,"bm":0,"nm":"Fill 1","mn":"ADBE Vector Graphic - Fill","hd":false},{"ty":"tr","p":{"a":0,"k":[275.031,290.588],"ix":2},"a":{"a":0,"k":[0,0],"ix":1},"s":{"a":0,"k":[100,100],"ix":3},"r":{"a":0,"k":0,"ix":6},"o":{"a":0,"k":100,"ix":7},"sk":{"a":0,"k":0,"ix":4},"sa":{"a":0,"k":0,"ix":5},"nm":"Transform"}],"nm":"Group 1","np":2,"cix":2,"bm":0,"ix":1,"mn":"ADBE Vector Group","hd":false},{"ty":"gr","it":[{"ind":0,"ty":"sh","ix":1,"ks":{"a":0,"k":{"i":[[0,0],[-22.043,-30.667],[27.772,40.993],[0,0],[3.72,-57.492]],"o":[[0,0],[22.043,30.667],[-27.771,-40.993],[0,0],[0,0]],"v":[[-94.836,27.922],[11.408,35.693],[68.291,-19.852],[4.257,-66.36],[-96.063,26.537]],"c":false},"ix":2},"nm":"Path 1","mn":"ADBE Vector Shape - Group","hd":false},{"ty":"fl","c":{"a":0,"k":[1,0.333333333333,0.20000001496,1],"ix":4},"o":{"a":0,"k":100,"ix":5},"r":1,"bm":0,"nm":"Fill 1","mn":"ADBE Vector Graphic - Fill","hd":false},{"ty":"tr","p":{"a":0,"k":[260.421,297.52],"ix":2},"a":{"a":0,"k":[0,0],"ix":1},"s":{"a":0,"k":[100,100],"ix":3},"r":{"a":0,"k":0,"ix":6},"o":{"a":0,"k":100,"ix":7},"sk":{"a":0,"k":0,"ix":4},"sa":{"a":0,"k":0,"ix":5},"nm":"Transform"}],"nm":"Group 2","np":2,"cix":2,"bm":0,"ix":2,"mn":"ADBE Vector Group","hd":false}],"ip":0,"op":90,"st":0,"bm":0},{"ddd":0,"ind":3,"ty":4,"nm":"Layer 6 Outlines","parent":1,"sr":1,"ks":{"o":{"a":0,"k":100,"ix":11},"r":{"a":0,"k":0,"ix":10},"p":{"a":0,"k":[250,250,0],"ix":2,"l":2},"a":{"a":0,"k":[250,250,0],"ix":1,"l":2},"s":{"a":0,"k":[100,100,100],"ix":6,"l":2}},"ao":0,"shapes":[{"ty":"gr","it":[{"ind":0,"ty":"sh","ix":1,"ks":{"a":0,"k":{"i":[[-27.257,2.548],[49.658,0],[14.037,38.458],[-42.64,0]],"o":[[-14.085,38.458],[-49.659,0],[27.257,2.548],[42.64,0]],"v":[[105.759,-33.194],[0,33.194],[-105.759,-33.194],[0,-30.021]],"c":true},"ix":2},"nm":"Path 1","mn":"ADBE Vector Shape - Group","hd":false},{"ty":"fl","c":{"a":0,"k":[0.827451040231,0.450980422076,0,1],"ix":4},"o":{"a":0,"k":100,"ix":5},"r":1,"bm":0,"nm":"Fill 1","mn":"ADBE Vector Graphic - Fill","hd":false},{"ty":"tr","p":{"a":0,"k":[250.024,380.397],"ix":2},"a":{"a":0,"k":[0,0],"ix":1},"s":{"a":0,"k":[100,100],"ix":3},"r":{"a":0,"k":0,"ix":6},"o":{"a":0,"k":100,"ix":7},"sk":{"a":0,"k":0,"ix":4},"sa":{"a":0,"k":0,"ix":5},"nm":"Transform"}],"nm":"Group 1","np":2,"cix":2,"bm":0,"ix":1,"mn":"ADBE Vector Group","hd":false}],"ip":0,"op":90,"st":0,"bm":0},{"ddd":0,"ind":4,"ty":4,"nm":"Layer 5 Outlines","sr":1,"ks":{"o":{"a":0,"k":100,"ix":11},"r":{"a":0,"k":0,"ix":10},"p":{"a":1,"k":[{"i":{"x":0.667,"y":1},"o":{"x":0.756,"y":0},"t":18,"s":[250,250,0],"to":[0,0,0],"ti":[0,0,0]},{"t":28,"s":[250,258,0]}],"ix":2,"l":2},"a":{"a":0,"k":[250,250,0],"ix":1,"l":2},"s":{"a":1,"k":[{"i":{"x":[0.667,0.667,0.667],"y":[1.003,1.003,1]},"o":{"x":[0.756,0.756,0.333],"y":[0,0,0]},"t":18,"s":[100,100,100]},{"t":28,"s":[142,142,100]}],"ix":6,"l":2}},"ao":0,"shapes":[{"ty":"gr","it":[{"ind":0,"ty":"sh","ix":1,"ks":{"a":0,"k":{"i":[[10.099,-10.099],[5.05,5.05],[-10.099,10.1],[-5.049,-5.05]],"o":[[-10.099,10.099],[-5.05,-5.049],[10.1,-10.099],[5.05,5.05]],"v":[[9.144,9.143],[-18.286,18.286],[-9.143,-9.144],[18.286,-18.287]],"c":true},"ix":2},"nm":"Path 1","mn":"ADBE Vector Shape - Group","hd":false},{"ty":"fl","c":{"a":0,"k":[0.956862804936,0.960784373564,0.941176530427,1],"ix":4},"o":{"a":0,"k":100,"ix":5},"r":1,"bm":0,"nm":"Fill 1","mn":"ADBE Vector Graphic - Fill","hd":false},{"ty":"tr","p":{"a":0,"k":[122.189,233.254],"ix":2},"a":{"a":0,"k":[0,0],"ix":1},"s":{"a":0,"k":[100,100],"ix":3},"r":{"a":0,"k":0,"ix":6},"o":{"a":0,"k":100,"ix":7},"sk":{"a":0,"k":0,"ix":4},"sa":{"a":0,"k":0,"ix":5},"nm":"Transform"}],"nm":"Group 1","np":2,"cix":2,"bm":0,"ix":1,"mn":"ADBE Vector Group","hd":false},{"ty":"gr","it":[{"ind":0,"ty":"sh","ix":1,"ks":{"a":0,"k":{"i":[[-10.099,-10.099],[5.05,-5.05],[10.1,10.099],[-5.05,5.049]],"o":[[10.099,10.099],[-5.049,5.05],[-10.099,-10.1],[5.05,-5.05]],"v":[[9.144,-9.144],[18.286,18.286],[-9.143,9.144],[-18.286,-18.286]],"c":true},"ix":2},"nm":"Path 1","mn":"ADBE Vector Shape - Group","hd":false},{"ty":"fl","c":{"a":0,"k":[0.956862804936,0.960784373564,0.941176530427,1],"ix":4},"o":{"a":0,"k":100,"ix":5},"r":1,"bm":0,"nm":"Fill 1","mn":"ADBE Vector Graphic - Fill","hd":false},{"ty":"tr","p":{"a":0,"k":[377.81,233.254],"ix":2},"a":{"a":0,"k":[0,0],"ix":1},"s":{"a":0,"k":[100,100],"ix":3},"r":{"a":0,"k":0,"ix":6},"o":{"a":0,"k":100,"ix":7},"sk":{"a":0,"k":0,"ix":4},"sa":{"a":0,"k":0,"ix":5},"nm":"Transform"}],"nm":"Group 2","np":2,"cix":2,"bm":0,"ix":2,"mn":"ADBE Vector Group","hd":false}],"ip":0,"op":90,"st":0,"bm":0},{"ddd":0,"ind":5,"ty":4,"nm":"Layer 4 Outlines","sr":1,"ks":{"o":{"a":0,"k":100,"ix":11},"r":{"a":0,"k":0,"ix":10},"p":{"a":1,"k":[{"i":{"x":0.667,"y":1},"o":{"x":0.756,"y":0},"t":18,"s":[250,250,0],"to":[0,0,0],"ti":[0,0,0]},{"t":28,"s":[250,275,0]}],"ix":2,"l":2},"a":{"a":0,"k":[250,250,0],"ix":1,"l":2},"s":{"a":1,"k":[{"i":{"x":[0.667,0.667,0.667],"y":[1.004,1.004,1]},"o":{"x":[0.756,0.756,0.333],"y":[0,0,0]},"t":18,"s":[100,100,100]},{"t":28,"s":[127,127,100]}],"ix":6,"l":2}},"ao":0,"shapes":[{"ty":"gr","it":[{"ind":0,"ty":"sh","ix":1,"ks":{"a":0,"k":{"i":[[0,-10.944],[10.944,0],[0,10.944],[-10.945,0]],"o":[[0,10.944],[-10.945,0],[0,-10.944],[10.944,0]],"v":[[19.817,0],[0.001,19.816],[-19.816,0],[0.001,-19.816]],"c":true},"ix":2},"nm":"Path 1","mn":"ADBE Vector Shape - Group","hd":false},{"ty":"fl","c":{"a":0,"k":[0.247058838489,0.247058838489,0.247058838489,1],"ix":4},"o":{"a":0,"k":100,"ix":5},"r":1,"bm":0,"nm":"Fill 1","mn":"ADBE Vector Graphic - Fill","hd":false},{"ty":"tr","p":{"a":0,"k":[90.398,204.956],"ix":2},"a":{"a":0,"k":[0,0],"ix":1},"s":{"a":0,"k":[100,100],"ix":3},"r":{"a":0,"k":0,"ix":6},"o":{"a":0,"k":100,"ix":7},"sk":{"a":0,"k":0,"ix":4},"sa":{"a":0,"k":0,"ix":5},"nm":"Transform"}],"nm":"Group 1","np":2,"cix":2,"bm":0,"ix":1,"mn":"ADBE Vector Group","hd":false},{"ty":"gr","it":[{"ind":0,"ty":"sh","ix":1,"ks":{"a":0,"k":{"i":[[0,-10.944],[10.944,0],[0,10.944],[-10.945,0]],"o":[[0,10.944],[-10.945,0],[0,-10.944],[10.944,0]],"v":[[19.817,0],[0.001,19.816],[-19.816,0],[0.001,-19.816]],"c":true},"ix":2},"nm":"Path 1","mn":"ADBE Vector Shape - Group","hd":false},{"ty":"fl","c":{"a":0,"k":[0.247058838489,0.247058838489,0.247058838489,1],"ix":4},"o":{"a":0,"k":100,"ix":5},"r":1,"bm":0,"nm":"Fill 1","mn":"ADBE Vector Graphic - Fill","hd":false},{"ty":"tr","p":{"a":0,"k":[409.602,204.956],"ix":2},"a":{"a":0,"k":[0,0],"ix":1},"s":{"a":0,"k":[100,100],"ix":3},"r":{"a":0,"k":0,"ix":6},"o":{"a":0,"k":100,"ix":7},"sk":{"a":0,"k":0,"ix":4},"sa":{"a":0,"k":0,"ix":5},"nm":"Transform"}],"nm":"Group 2","np":2,"cix":2,"bm":0,"ix":2,"mn":"ADBE Vector Group","hd":false}],"ip":0,"op":90,"st":0,"bm":0},{"ddd":0,"ind":6,"ty":4,"nm":"Layer 3 Outlines","sr":1,"ks":{"o":{"a":0,"k":100,"ix":11},"r":{"a":0,"k":0,"ix":10},"p":{"a":1,"k":[{"i":{"x":0.667,"y":1},"o":{"x":0.756,"y":0},"t":18,"s":[250,250,0],"to":[0,0,0],"ti":[0,0,0]},{"t":28,"s":[250,260,0]}],"ix":2,"l":2},"a":{"a":0,"k":[250,250,0],"ix":1,"l":2},"s":{"a":0,"k":[100,100,100],"ix":6,"l":2}},"ao":0,"shapes":[{"ty":"gr","it":[{"ind":0,"ty":"sh","ix":1,"ks":{"a":0,"k":{"i":[[0,-74.742],[74.742,0],[0,74.742],[-74.742,0]],"o":[[0,74.742],[-74.742,0],[0,-74.742],[74.742,0]],"v":[[135.333,0],[0,135.333],[-135.333,0],[0,-135.333]],"c":true},"ix":2},"nm":"Path 1","mn":"ADBE Vector Shape - Group","hd":false},{"ty":"fl","c":{"a":0,"k":[0.956862804936,0.960784373564,0.941176530427,1],"ix":4},"o":{"a":0,"k":100,"ix":5},"r":1,"bm":0,"nm":"Fill 1","mn":"ADBE Vector Graphic - Fill","hd":false},{"ty":"tr","p":{"a":0,"k":[339.21,296.483],"ix":2},"a":{"a":0,"k":[0,0],"ix":1},"s":{"a":0,"k":[100,100],"ix":3},"r":{"a":0,"k":0,"ix":6},"o":{"a":0,"k":100,"ix":7},"sk":{"a":0,"k":0,"ix":4},"sa":{"a":0,"k":0,"ix":5},"nm":"Transform"}],"nm":"Group 1","np":2,"cix":2,"bm":0,"ix":1,"mn":"ADBE Vector Group","hd":false},{"ty":"gr","it":[{"ind":0,"ty":"sh","ix":1,"ks":{"a":0,"k":{"i":[[0,-74.742],[74.742,0],[0,74.742],[-74.742,0]],"o":[[0,74.742],[-74.742,0],[0,-74.742],[74.742,0]],"v":[[135.333,0],[0,135.333],[-135.333,0],[0,-135.333]],"c":true},"ix":2},"nm":"Path 1","mn":"ADBE Vector Shape - Group","hd":false},{"ty":"fl","c":{"a":0,"k":[0.956862804936,0.960784373564,0.941176530427,1],"ix":4},"o":{"a":0,"k":100,"ix":5},"r":1,"bm":0,"nm":"Fill 1","mn":"ADBE Vector Graphic - Fill","hd":false},{"ty":"tr","p":{"a":0,"k":[160.791,296.483],"ix":2},"a":{"a":0,"k":[0,0],"ix":1},"s":{"a":0,"k":[100,100],"ix":3},"r":{"a":0,"k":0,"ix":6},"o":{"a":0,"k":100,"ix":7},"sk":{"a":0,"k":0,"ix":4},"sa":{"a":0,"k":0,"ix":5},"nm":"Transform"}],"nm":"Group 2","np":2,"cix":2,"bm":0,"ix":2,"mn":"ADBE Vector Group","hd":false}],"ip":0,"op":90,"st":0,"bm":0},{"ddd":0,"ind":7,"ty":4,"nm":"Layer 2 Outlines","sr":1,"ks":{"o":{"a":0,"k":100,"ix":11},"r":{"a":0,"k":0,"ix":10},"p":{"a":0,"k":[250,250,0],"ix":2,"l":2},"a":{"a":0,"k":[250,250,0],"ix":1,"l":2},"s":{"a":0,"k":[100,100,100],"ix":6,"l":2}},"ao":0,"shapes":[{"ty":"gr","it":[{"ind":0,"ty":"sh","ix":1,"ks":{"a":0,"k":{"i":[[0,-115.469],[115.469,0],[0,115.469],[-115.468,0]],"o":[[0,115.469],[-115.468,0],[0,-115.469],[115.469,0]],"v":[[209.074,0],[-0.001,209.075],[-209.074,0],[-0.001,-209.075]],"c":true},"ix":2},"nm":"Path 1","mn":"ADBE Vector Shape - Group","hd":false},{"ty":"fl","c":{"a":0,"k":[0.956862804936,0.960784373564,0.941176530427,1],"ix":4},"o":{"a":0,"k":100,"ix":5},"r":1,"bm":0,"nm":"Fill 1","mn":"ADBE Vector Graphic - Fill","hd":false},{"ty":"tr","p":{"a":0,"k":[250,250],"ix":2},"a":{"a":0,"k":[0,0],"ix":1},"s":{"a":0,"k":[100,100],"ix":3},"r":{"a":0,"k":0,"ix":6},"o":{"a":0,"k":100,"ix":7},"sk":{"a":0,"k":0,"ix":4},"sa":{"a":0,"k":0,"ix":5},"nm":"Transform"}],"nm":"Group 1","np":2,"cix":2,"bm":0,"ix":1,"mn":"ADBE Vector Group","hd":false}],"ip":0,"op":90,"st":0,"bm":0},{"ddd":0,"ind":8,"ty":4,"nm":"Layer 1 Outlines","sr":1,"ks":{"o":{"a":0,"k":100,"ix":11},"r":{"a":0,"k":0,"ix":10},"p":{"a":0,"k":[250,250,0],"ix":2,"l":2},"a":{"a":0,"k":[250,250,0],"ix":1,"l":2},"s":{"a":0,"k":[100,100,100],"ix":6,"l":2}},"ao":0,"shapes":[{"ty":"gr","it":[{"ind":0,"ty":"sh","ix":1,"ks":{"a":0,"k":{"i":[[9.065,-9.065],[4.533,4.533],[-9.065,9.065],[-4.533,-4.533]],"o":[[-9.065,9.065],[-4.533,-4.533],[9.065,-9.065],[4.533,4.533]],"v":[[8.207,8.207],[-16.414,16.414],[-8.207,-8.207],[16.414,-16.414]],"c":true},"ix":2},"nm":"Path 1","mn":"ADBE Vector Shape - Group","hd":false},{"ty":"fl","c":{"a":0,"k":[0.956862804936,0.960784373564,0.941176530427,1],"ix":4},"o":{"a":0,"k":100,"ix":5},"r":1,"bm":0,"nm":"Fill 1","mn":"ADBE Vector Graphic - Fill","hd":false},{"ty":"tr","p":{"a":0,"k":[135.277,212.805],"ix":2},"a":{"a":0,"k":[0,0],"ix":1},"s":{"a":0,"k":[100,100],"ix":3},"r":{"a":0,"k":0,"ix":6},"o":{"a":0,"k":100,"ix":7},"sk":{"a":0,"k":0,"ix":4},"sa":{"a":0,"k":0,"ix":5},"nm":"Transform"}],"nm":"Group 1","np":2,"cix":2,"bm":0,"ix":1,"mn":"ADBE Vector Group","hd":false},{"ty":"gr","it":[{"ind":0,"ty":"sh","ix":1,"ks":{"a":0,"k":{"i":[[-9.065,-9.065],[4.533,-4.533],[9.065,9.065],[-4.533,4.533]],"o":[[9.065,9.065],[-4.533,4.533],[-9.065,-9.065],[4.533,-4.533]],"v":[[8.207,-8.207],[16.414,16.414],[-8.207,8.207],[-16.414,-16.414]],"c":true},"ix":2},"nm":"Path 1","mn":"ADBE Vector Shape - Group","hd":false},{"ty":"fl","c":{"a":0,"k":[0.956862804936,0.960784373564,0.941176530427,1],"ix":4},"o":{"a":0,"k":100,"ix":5},"r":1,"bm":0,"nm":"Fill 1","mn":"ADBE Vector Graphic - Fill","hd":false},{"ty":"tr","p":{"a":0,"k":[364.723,212.805],"ix":2},"a":{"a":0,"k":[0,0],"ix":1},"s":{"a":0,"k":[100,100],"ix":3},"r":{"a":0,"k":0,"ix":6},"o":{"a":0,"k":100,"ix":7},"sk":{"a":0,"k":0,"ix":4},"sa":{"a":0,"k":0,"ix":5},"nm":"Transform"}],"nm":"Group 2","np":2,"cix":2,"bm":0,"ix":2,"mn":"ADBE Vector Group","hd":false}],"ip":0,"op":90,"st":0,"bm":0}],"markers":[]}